aws_content_mcp/__init__.py
aws_content_mcp/config.py
aws_content_mcp/content_fetcher.py
aws_content_mcp/server.py
aws_content_mcp-0.1.1.dist-info/METADATA
aws_content_mcp-0.1.1.dist-info/WHEEL
aws_content_mcp-0.1.1.dist-info/entry_points.txt
aws_content_mcp-0.1.1.dist-info/licenses/LICENSE
aws_content_mcp-0.1.1.dist-info/RECORD
