Metadata-Version: 2.4
Name: aws-content-mcp
Version: 0.1.1
Summary: MCP server for retrieving and analyzing AWS content from aws.amazon.com
Project-URL: Homepage, https://github.com/aws-content-mcp/aws-content-mcp
Project-URL: Repository, https://github.com/aws-content-mcp/aws-content-mcp
Project-URL: Issues, https://github.com/aws-content-mcp/aws-content-mcp/issues
Author-email: AWS Content MCP <aws-content-mcp@example.com>
License: MIT
License-File: LICENSE
Classifier: Development Status :: 3 - Alpha
Classifier: Intended Audience :: Developers
Classifier: License :: OSI Approved :: MIT License
Classifier: Programming Language :: Python :: 3
Classifier: Programming Language :: Python :: 3.8
Classifier: Programming Language :: Python :: 3.9
Classifier: Programming Language :: Python :: 3.10
Classifier: Programming Language :: Python :: 3.11
Classifier: Programming Language :: Python :: 3.12
Requires-Python: >=3.8
Requires-Dist: aiofiles>=23.0.0
Requires-Dist: beautifulsoup4>=4.12.0
Requires-Dist: httpx>=0.25.0
Requires-Dist: lxml>=4.9.0
Requires-Dist: markdownify>=0.11.0
Requires-Dist: mcp>=1.0.0
Requires-Dist: pydantic>=2.0.0
Requires-Dist: python-dateutil>=2.8.0
Requires-Dist: readability-lxml>=0.8.0
Requires-Dist: urllib3>=2.0.0
Provides-Extra: dev
Requires-Dist: black>=23.0.0; extra == 'dev'
Requires-Dist: isort>=5.12.0; extra == 'dev'
Requires-Dist: mypy>=1.5.0; extra == 'dev'
Requires-Dist: pre-commit>=3.0.0; extra == 'dev'
Requires-Dist: pytest-asyncio>=0.21.0; extra == 'dev'
Requires-Dist: pytest>=7.0.0; extra == 'dev'
